spatialstats/Configuration.py
spatialstats/__init__.py
spatialstats/particles/__init__.py
spatialstats/particles/particle_cloud.py
spatialstats/particles/particle_correlations.py
spatialstats/points/__init__.py
spatialstats/points/point_cloud.py
spatialstats/points/structure_factor.py
spatialstats/polyspectra/__init__.py
spatialstats/polyspectra/bispectrum.py
spatialstats/polyspectra/cuda_bispectrum.py
spatialstats/polyspectra/cuda_powerspectrum.py
spatialstats/polyspectra/powerspectrum.py
spatialstats/utils/__init__.py
spatialstats/utils/binning.py
spatialstats-1.1.2.dist-info/LICENSE
spatialstats-1.1.2.dist-info/METADATA
spatialstats-1.1.2.dist-info/WHEEL
spatialstats-1.1.2.dist-info/top_level.txt
spatialstats-1.1.2.dist-info/RECORD
