Metadata-Version: 2.1
Name: spatialstats
Version: 1.1.2
Summary: Statistical routines to analyze the spatial structure of 2D and 3D spatial fields and particle distributions.
Home-page: https://github.com/mjo22/spatialstats
Author: Michael O'Brien
License: MIT
Keywords: correlation-functions bispectrum statistical-mechanics particle-simulation
Platform: UNKNOWN
Classifier: Programming Language :: Python :: 3 :: Only
Classifier: Programming Language :: Python :: 3.7
Classifier: Programming Language :: Python :: 3.8
Classifier: Programming Language :: Python :: 3.9
Classifier: License :: OSI Approved :: MIT License
Requires-Python: >=3.7
Requires-Dist: numpy
Provides-Extra: cpu
Requires-Dist: scipy ; extra == 'cpu'
Requires-Dist: numba (>=0.50) ; extra == 'cpu'
Requires-Dist: pyfftw ; extra == 'cpu'
Provides-Extra: full
Requires-Dist: scipy ; extra == 'full'
Requires-Dist: numba (>=0.50) ; extra == 'full'
Requires-Dist: cupy (>=8.0) ; extra == 'full'
Requires-Dist: pyfftw ; extra == 'full'
Provides-Extra: gpu
Requires-Dist: cupy (>=8.0) ; extra == 'gpu'
